[
  {
    "username": "member777",
    "phone": "+923001234567",
    "password": "password123",
    "securityQuestion": "What was your childhood nickname?",
    "securityAnswer": "latigomusic",
    "referralCodeOwned": "LATIGO50K",
    "balance": 0,
    "vipLevel": 1,
    "isBanned": false,
    "transactions": [],
    "completedTasks": 0,
    "hasClaimedWelfare": false,
    "investmentBalance": 0,
    "vip": 1
  },
  {
    "username": "music_listener",
    "phone": "+923000000000",
    "password": "user123",
    "balance": 155.4,
    "vipLevel": 2,
    "registrationDate": "2026-04-01 12:00",
    "isBanned": false,
    "referralCodeOwned": "MUSIC777",
    "completedTasks": 12,
    "transactions": [],
    "hasClaimedWelfare": false,
    "investmentBalance": 155.4,
    "vip": 2
  },
  {
    "username": "john_doe",
    "phone": "+14155552671",
    "password": "password123",
    "balance": 45,
    "vipLevel": 1,
    "registrationDate": "2026-04-03 09:30",
    "isBanned": false,
    "referralCodeOwned": "JD999",
    "completedTasks": 5,
    "transactions": [],
    "hasClaimedWelfare": false,
    "investmentBalance": 45,
    "vip": 1
  },
  {
    "username": "kashif_officer",
    "phone": "+923214567890",
    "password": "kashif999",
    "balance": 2500,
    "vipLevel": 3,
    "registrationDate": "2026-03-29 16:15",
    "isBanned": false,
    "referralCodeOwned": "KASH92",
    "completedTasks": 42,
    "transactions": [],
    "hasClaimedWelfare": false,
    "investmentBalance": 2500,
    "vip": 3
  },
  {
    "username": "spammer_account",
    "phone": "+923330001112",
    "password": "spam",
    "balance": 0,
    "vipLevel": 1,
    "registrationDate": "2026-04-05 14:10",
    "isBanned": true,
    "referralCodeOwned": "SPAM1",
    "completedTasks": 0,
    "transactions": [],
    "hasClaimedWelfare": false,
    "investmentBalance": 0,
    "vip": 1
  }
]